{
    "openapi": "3.0.0",
    "info": {
        "title": "MovieFlix API",
        "description": "API para gerenciamento de filmes do MovieFlix",
        "version": "1.0.0"
    },
    "paths": {
        "/movies": {
            "get": {
                "tags": ["Movie"],
                "summary": "Obter todos os filmes",
                "description": "Retorna uma lista de filmes disponíveis no MovieFlix",
                "responses": {
                    "200": {
                        "description": "Lista de filmes retornada com sucesso",
                        "content": {
                            "application/json": {
                                "schema": {
                                    "type": "array",
                                    "items": {
                                        "$ref": "#/components/schemas/Movie"
                                    }
                                }
                            }
                        }
                    }
                }
            }
        }
    },
    "components": {
        "schemas": {
            "Movie": {
                "type": "object",
                "properties": {
                    "id": {
                        "type": "integer",
                        "description": "ID do filme"
                    },
                    "title": {
                        "type": "string",
                        "description": "Título do filme"
                    },
                    "genre_id": {
                        "type": "integer",
                        "description": "Gênero do filme"
                    },
                    "genres": {
                        "type": "object",
                        "properties": {
                            "id": {
                                "type": "integer",
                                "description": "ID do gênero"
                            },
                            "name": {
                                "type": "string",
                                "description": "Nome do gênero"
                            }
                        }
                    },
                    "language_id": {
                        "type": "integer",
                        "description": "Idiomas do filme"
                    },
                        "languages": {
                        "type": "object",
                        "properties": {
                            "id": {
                                "type": "integer",
                                "description": "ID do idioma"
                            },
                            "name": {
                                "type": "string",
                                "description": "Nome do idioma"
                            }
                        }
                    },
                    "oscar_count": {
                        "type": "integer",
                        "description": "Número de Oscars ganhos pelo filme"
                    },
                    "release_date": {
                        "type": "string",
                        "format": "date",
                        "description": "Data de lançamento do filme"
                    }
                }
            }
        }
    }
}